{"direction": "South", "Number": 380, "LongName": "Interstate 380 (Iowa)", "Path": [{"lat": 42.47662, "lon": -92.32212, "id": 73999.0, "indx": 0}, {"lat": 42.47459, "lon": -92.32207, "id": 74000.0, "indx": 1}, {"lat": 42.47338, "lon": -92.32195, "id": 74001.0, "indx": 2}, {"lat": 42.46558, "lon": -92.31616, "id": 74002.0, "indx": 3}, {"lat": 42.4638, "lon": -92.31499, "id": 74003.0, "indx": 4}, {"lat": 42.46184, "lon": -92.31441, "id": 74004.0, "indx": 5}, {"lat": 42.45823, "lon": -92.31348, "id": 74005.0, "indx": 6}, {"lat": 42.45666, "lon": -92.31226, "id": 74006.0, "indx": 7}, {"lat": 42.45585, "lon": -92.31096, "id": 74007.0, "indx": 8}, {"lat": 42.4555, "lon": -92.30869, "id": 74008.0, "indx": 9}, {"lat": 42.45609, "lon": -92.30634, "id": 74009.0, "indx": 10}, {"lat": 42.45861, "lon": -92.29877, "id": 74010.0, "indx": 11}, {"lat": 42.45948, "lon": -92.29518, "id": 74011.0, "indx": 12}, {"lat": 42.45992, "lon": -92.28912, "id": 74012.0, "indx": 13}, {"lat": 42.4605, "lon": -92.28094, "id": 74013.0, "indx": 14}, {"lat": 42.46038, "lon": -92.26731, "id": 74014.0, "indx": 15}, {"lat": 42.46029, "lon": -92.26327, "id": 74015.0, "indx": 16}, {"lat": 42.45979, "lon": -92.26021, "id": 74016.0, "indx": 17}, {"lat": 42.45894, "lon": -92.25733, "id": 74017.0, "indx": 18}, {"lat": 42.45777, "lon": -92.2544, "id": 74018.0, "indx": 19}, {"lat": 42.45658, "lon": -92.25234, "id": 74019.0, "indx": 20}, {"lat": 42.45457, "lon": -92.24926, "id": 74020.0, "indx": 21}, {"lat": 42.45344, "lon": -92.24693, "id": 74021.0, "indx": 22}, {"lat": 42.45251, "lon": -92.24431, "id": 74022.0, "indx": 23}, {"lat": 42.45179, "lon": -92.24138, "id": 74023.0, "indx": 24}, {"lat": 42.45137, "lon": -92.23782, "id": 74024.0, "indx": 25}, {"lat": 42.44949, "lon": -92.22008, "id": 74025.0, "indx": 26}, {"lat": 42.44942, "lon": -92.21538, "id": 74026.0, "indx": 27}, {"lat": 42.44934, "lon": -92.20615, "id": 74027.0, "indx": 28}, {"lat": 42.44932, "lon": -92.19792, "id": 74028.0, "indx": 29}, {"lat": 42.44823, "lon": -92.19463, "id": 74029.0, "indx": 30}, {"lat": 42.44666, "lon": -92.19265, "id": 74030.0, "indx": 31}, {"lat": 42.44459, "lon": -92.19078, "id": 74031.0, "indx": 32}, {"lat": 42.4418, "lon": -92.18888, "id": 74032.0, "indx": 33}, {"lat": 42.43589, "lon": -92.18787, "id": 74033.0, "indx": 34}, {"lat": 42.42655, "lon": -92.18636, "id": 74034.0, "indx": 35}, {"lat": 42.42476, "lon": -92.18578, "id": 74035.0, "indx": 36}, {"lat": 42.42273, "lon": -92.18447, "id": 74036.0, "indx": 37}, {"lat": 42.42118, "lon": -92.18282, "id": 74037.0, "indx": 38}, {"lat": 42.41454, "lon": -92.17343, "id": 74038.0, "indx": 39}, {"lat": 42.40663, "lon": -92.16238, "id": 74039.0, "indx": 40}, {"lat": 42.40072, "lon": -92.1523, "id": 74040.0, "indx": 41}, {"lat": 42.38983, "lon": -92.13354, "id": 74041.0, "indx": 42}, {"lat": 42.3788, "lon": -92.11465, "id": 74042.0, "indx": 43}, {"lat": 42.37252, "lon": -92.10381, "id": 74043.0, "indx": 44}, {"lat": 42.36709, "lon": -92.09268, "id": 74044.0, "indx": 45}, {"lat": 42.35992, "lon": -92.07961, "id": 74045.0, "indx": 46}, {"lat": 42.35891, "lon": -92.07762, "id": 74046.0, "indx": 47}, {"lat": 42.35731, "lon": -92.07355, "id": 74047.0, "indx": 48}, {"lat": 42.34727, "lon": -92.04691, "id": 74048.0, "indx": 49}, {"lat": 42.33795, "lon": -92.02219, "id": 74049.0, "indx": 50}, {"lat": 42.33013, "lon": -92.00124, "id": 74050.0, "indx": 51}, {"lat": 42.32879, "lon": -91.99853, "id": 74051.0, "indx": 52}, {"lat": 42.32742, "lon": -91.99648, "id": 74052.0, "indx": 53}, {"lat": 42.31597, "lon": -91.98241, "id": 74053.0, "indx": 54}, {"lat": 42.30419, "lon": -91.96799, "id": 74054.0, "indx": 55}, {"lat": 42.29386, "lon": -91.9554, "id": 74055.0, "indx": 56}, {"lat": 42.28195, "lon": -91.94085, "id": 74056.0, "indx": 57}, {"lat": 42.28041, "lon": -91.93879, "id": 74057.0, "indx": 58}, {"lat": 42.27849, "lon": -91.93515, "id": 74058.0, "indx": 59}, {"lat": 42.27649, "lon": -91.93129, "id": 74059.0, "indx": 60}, {"lat": 42.2748, "lon": -91.9286, "id": 74060.0, "indx": 61}, {"lat": 42.2636, "lon": -91.91455, "id": 74061.0, "indx": 62}, {"lat": 42.2506, "lon": -91.8981, "id": 74062.0, "indx": 63}, {"lat": 42.23875, "lon": -91.88322, "id": 74063.0, "indx": 64}, {"lat": 42.23688, "lon": -91.88068, "id": 74064.0, "indx": 65}, {"lat": 42.23042, "lon": -91.87002, "id": 74065.0, "indx": 66}, {"lat": 42.21854, "lon": -91.85023, "id": 74066.0, "indx": 67}, {"lat": 42.21626, "lon": -91.8465, "id": 74067.0, "indx": 68}, {"lat": 42.21402, "lon": -91.8433, "id": 74068.0, "indx": 69}, {"lat": 42.20176, "lon": -91.82982, "id": 74069.0, "indx": 70}, {"lat": 42.1991, "lon": -91.82672, "id": 74070.0, "indx": 71}, {"lat": 42.19746, "lon": -91.82416, "id": 74071.0, "indx": 72}, {"lat": 42.18824, "lon": -91.80557, "id": 74072.0, "indx": 73}, {"lat": 42.1856, "lon": -91.80069, "id": 74073.0, "indx": 74}, {"lat": 42.1804, "lon": -91.79327, "id": 74074.0, "indx": 75}, {"lat": 42.16856, "lon": -91.77656, "id": 74075.0, "indx": 76}, {"lat": 42.16664, "lon": -91.7734, "id": 74076.0, "indx": 77}, {"lat": 42.15908, "lon": -91.75849, "id": 74077.0, "indx": 78}, {"lat": 42.15738, "lon": -91.75558, "id": 74078.0, "indx": 79}, {"lat": 42.15574, "lon": -91.75357, "id": 74079.0, "indx": 80}, {"lat": 42.14614, "lon": -91.74428, "id": 74080.0, "indx": 81}, {"lat": 42.13323, "lon": -91.73092, "id": 74081.0, "indx": 82}, {"lat": 42.13181, "lon": -91.729, "id": 74082.0, "indx": 83}, {"lat": 42.12988, "lon": -91.7245, "id": 74083.0, "indx": 84}, {"lat": 42.12824, "lon": -91.72092, "id": 74084.0, "indx": 85}, {"lat": 42.12679, "lon": -91.71873, "id": 74085.0, "indx": 86}, {"lat": 42.12501, "lon": -91.71703, "id": 74086.0, "indx": 87}, {"lat": 42.11654, "lon": -91.71162, "id": 74087.0, "indx": 88}, {"lat": 42.10336, "lon": -91.70331, "id": 74088.0, "indx": 89}, {"lat": 42.10164, "lon": -91.70232, "id": 74089.0, "indx": 90}, {"lat": 42.09992, "lon": -91.70175, "id": 74090.0, "indx": 91}, {"lat": 42.08837, "lon": -91.70143, "id": 74091.0, "indx": 92}, {"lat": 42.07702, "lon": -91.7011, "id": 74092.0, "indx": 93}, {"lat": 42.07, "lon": -91.70065, "id": 74093.0, "indx": 94}, {"lat": 42.05839, "lon": -91.69988, "id": 74094.0, "indx": 95}, {"lat": 42.05632, "lon": -91.69943, "id": 74095.0, "indx": 96}, {"lat": 42.05459, "lon": -91.6985, "id": 74096.0, "indx": 97}, {"lat": 42.0531, "lon": -91.69733, "id": 74097.0, "indx": 98}, {"lat": 42.05192, "lon": -91.69598, "id": 74098.0, "indx": 99}, {"lat": 42.05062, "lon": -91.69401, "id": 74099.0, "indx": 100}, {"lat": 42.04292, "lon": -91.68047, "id": 74100.0, "indx": 101}, {"lat": 42.04174, "lon": -91.67875, "id": 74101.0, "indx": 102}, {"lat": 42.04051, "lon": -91.67776, "id": 74102.0, "indx": 103}, {"lat": 42.03904, "lon": -91.67725, "id": 74103.0, "indx": 104}, {"lat": 42.03346, "lon": -91.67554, "id": 74104.0, "indx": 105}, {"lat": 42.03024, "lon": -91.67416, "id": 74105.0, "indx": 106}, {"lat": 42.0251, "lon": -91.6709, "id": 74106.0, "indx": 107}, {"lat": 42.01942, "lon": -91.66721, "id": 74107.0, "indx": 108}, {"lat": 42.01751, "lon": -91.66678, "id": 74108.0, "indx": 109}, {"lat": 42.01422, "lon": -91.66693, "id": 74109.0, "indx": 110}, {"lat": 42.00869, "lon": -91.66606, "id": 74110.0, "indx": 111}, {"lat": 42.00288, "lon": -91.66655, "id": 74111.0, "indx": 112}, {"lat": 41.99731, "lon": -91.66693, "id": 74112.0, "indx": 113}, {"lat": 41.99588, "lon": -91.66673, "id": 74113.0, "indx": 114}, {"lat": 41.99471, "lon": -91.66618, "id": 74114.0, "indx": 115}, {"lat": 41.99142, "lon": -91.663, "id": 74115.0, "indx": 116}, {"lat": 41.98991, "lon": -91.66171, "id": 74116.0, "indx": 117}, {"lat": 41.98862, "lon": -91.66134, "id": 74117.0, "indx": 118}, {"lat": 41.9874, "lon": -91.66149, "id": 74118.0, "indx": 119}, {"lat": 41.98608, "lon": -91.66217, "id": 74119.0, "indx": 120}, {"lat": 41.98128, "lon": -91.66748, "id": 74120.0, "indx": 121}, {"lat": 41.98041, "lon": -91.66868, "id": 74121.0, "indx": 122}, {"lat": 41.97818, "lon": -91.67448, "id": 74122.0, "indx": 123}, {"lat": 41.97732, "lon": -91.67563, "id": 74123.0, "indx": 124}, {"lat": 41.97624, "lon": -91.67618, "id": 74124.0, "indx": 125}, {"lat": 41.97519, "lon": -91.67624, "id": 74125.0, "indx": 126}, {"lat": 41.97428, "lon": -91.67589, "id": 74126.0, "indx": 127}, {"lat": 41.9679, "lon": -91.67136, "id": 74127.0, "indx": 128}, {"lat": 41.96655, "lon": -91.67075, "id": 74128.0, "indx": 129}, {"lat": 41.96303, "lon": -91.67075, "id": 74129.0, "indx": 130}, {"lat": 41.94841, "lon": -91.67101, "id": 74130.0, "indx": 131}, {"lat": 41.94695, "lon": -91.67082, "id": 74131.0, "indx": 132}, {"lat": 41.93764, "lon": -91.66904, "id": 74132.0, "indx": 133}, {"lat": 41.93628, "lon": -91.66895, "id": 74133.0, "indx": 134}, {"lat": 41.93, "lon": -91.66956, "id": 74134.0, "indx": 135}, {"lat": 41.91212, "lon": -91.67161, "id": 74135.0, "indx": 136}, {"lat": 41.90783, "lon": -91.672, "id": 74136.0, "indx": 137}, {"lat": 41.90574, "lon": -91.67211, "id": 74137.0, "indx": 138}, {"lat": 41.90312, "lon": -91.67194, "id": 74138.0, "indx": 139}, {"lat": 41.89033, "lon": -91.67085, "id": 74139.0, "indx": 140}, {"lat": 41.87657, "lon": -91.6703, "id": 74140.0, "indx": 141}, {"lat": 41.86537, "lon": -91.66926, "id": 74141.0, "indx": 142}, {"lat": 41.85123, "lon": -91.66789, "id": 74142.0, "indx": 143}, {"lat": 41.84811, "lon": -91.66746, "id": 74143.0, "indx": 144}, {"lat": 41.84538, "lon": -91.66659, "id": 74144.0, "indx": 145}, {"lat": 41.83465, "lon": -91.66292, "id": 74145.0, "indx": 146}, {"lat": 41.83143, "lon": -91.66136, "id": 74146.0, "indx": 147}, {"lat": 41.81676, "lon": -91.65317, "id": 74147.0, "indx": 148}, {"lat": 41.80695, "lon": -91.64767, "id": 74148.0, "indx": 149}, {"lat": 41.80491, "lon": -91.64686, "id": 74149.0, "indx": 150}, {"lat": 41.80349, "lon": -91.64649, "id": 74150.0, "indx": 151}, {"lat": 41.80211, "lon": -91.6464, "id": 74151.0, "indx": 152}, {"lat": 41.79344, "lon": -91.64687, "id": 74152.0, "indx": 153}, {"lat": 41.79203, "lon": -91.64683, "id": 74153.0, "indx": 154}, {"lat": 41.7753, "lon": -91.64661, "id": 74154.0, "indx": 155}, {"lat": 41.77311, "lon": -91.64648, "id": 74155.0, "indx": 156}, {"lat": 41.77149, "lon": -91.64621, "id": 74156.0, "indx": 157}, {"lat": 41.76956, "lon": -91.64548, "id": 74157.0, "indx": 158}, {"lat": 41.76712, "lon": -91.64408, "id": 74158.0, "indx": 159}, {"lat": 41.76489, "lon": -91.643, "id": 74159.0, "indx": 160}, {"lat": 41.76293, "lon": -91.64232, "id": 74160.0, "indx": 161}, {"lat": 41.76089, "lon": -91.64207, "id": 74161.0, "indx": 162}, {"lat": 41.75591, "lon": -91.6421, "id": 74162.0, "indx": 163}, {"lat": 41.73823, "lon": -91.64247, "id": 74163.0, "indx": 164}, {"lat": 41.72302, "lon": -91.64208, "id": 74164.0, "indx": 165}, {"lat": 41.70802, "lon": -91.64217, "id": 74165.0, "indx": 166}, {"lat": 41.70219, "lon": -91.64212, "id": 74166.0, "indx": 167}, {"lat": 41.70084, "lon": -91.64179, "id": 74167.0, "indx": 168}, {"lat": 41.69436, "lon": -91.63824, "id": 74168.0, "indx": 169}], "ShortName": "I-380", "Cities": {"With": [{"layer": 1, "StopIndex": 122, "cityName": "Cedar Rapids", "StartIndex": 21, "cityID": 1840000471, "length": 76.597}, {"layer": 2, "StopIndex": 122, "cityName": "Waterloo", "StartIndex": 63, "cityID": 1840000440, "length": 38.295}, {"layer": 1, "StopIndex": 168, "cityName": "Iowa City", "StartIndex": 123, "cityID": 1840000532, "length": 31.431}, {"layer": 1, "StopIndex": 20, "cityName": "Waterloo", "StartIndex": 7, "cityID": 1840000440, "length": 5.153}, {"layer": 1, "StopIndex": 6, "cityName": "Cedar Rapids", "StartIndex": 0, "cityID": 1840000471, "length": 2.203}, {"layer": 2, "StopIndex": 6, "cityName": "Dubuque", "StartIndex": 0, "cityID": 1840000438, "length": 2.203}], "Against": [{"layer": 1, "StopIndex": 0, "cityName": "Waterloo", "StartIndex": 122, "cityID": 1840000440, "length": 84.493}, {"layer": 1, "StopIndex": 57, "cityName": "Cedar Rapids", "StartIndex": 136, "cityID": 1840000471, "length": 51.334}, {"layer": 1, "StopIndex": 137, "cityName": "Waterloo", "StartIndex": 168, "cityID": 1840000440, "length": 23.425}]}, "id": 156}