{"direction": "East", "Number": 280, "LongName": "Interstate 280 (Illinois-Iowa)", "Path": [{"lat": 41.60362, "lon": -90.67625, "id": 175230.0, "indx": 0}, {"lat": 41.59508, "lon": -90.67606, "id": 175231.0, "indx": 1}, {"lat": 41.59096, "lon": -90.67588, "id": 175232.0, "indx": 2}, {"lat": 41.58733, "lon": -90.67595, "id": 175233.0, "indx": 3}, {"lat": 41.58444, "lon": -90.67605, "id": 175234.0, "indx": 4}, {"lat": 41.57991, "lon": -90.6768, "id": 175235.0, "indx": 5}, {"lat": 41.56966, "lon": -90.67857, "id": 175236.0, "indx": 6}, {"lat": 41.56734, "lon": -90.67892, "id": 175237.0, "indx": 7}, {"lat": 41.56531, "lon": -90.67896, "id": 175238.0, "indx": 8}, {"lat": 41.55708, "lon": -90.67842, "id": 175239.0, "indx": 9}, {"lat": 41.55393, "lon": -90.6781, "id": 175240.0, "indx": 10}, {"lat": 41.54988, "lon": -90.67806, "id": 175241.0, "indx": 11}, {"lat": 41.54453, "lon": -90.67815, "id": 175242.0, "indx": 12}, {"lat": 41.54265, "lon": -90.67798, "id": 175243.0, "indx": 13}, {"lat": 41.5329, "lon": -90.67551, "id": 175244.0, "indx": 14}, {"lat": 41.52748, "lon": -90.67421, "id": 175245.0, "indx": 15}, {"lat": 41.5262, "lon": -90.67406, "id": 175246.0, "indx": 16}, {"lat": 41.52456, "lon": -90.67403, "id": 175247.0, "indx": 17}, {"lat": 41.51632, "lon": -90.67447, "id": 175248.0, "indx": 18}, {"lat": 41.51473, "lon": -90.67447, "id": 175249.0, "indx": 19}, {"lat": 41.51346, "lon": -90.67439, "id": 175250.0, "indx": 20}, {"lat": 41.5053, "lon": -90.67141, "id": 175251.0, "indx": 21}, {"lat": 41.50394, "lon": -90.67044, "id": 175252.0, "indx": 22}, {"lat": 41.50284, "lon": -90.66918, "id": 175253.0, "indx": 23}, {"lat": 41.50166, "lon": -90.66737, "id": 175254.0, "indx": 24}, {"lat": 41.49765, "lon": -90.65925, "id": 175255.0, "indx": 25}, {"lat": 41.49575, "lon": -90.65614, "id": 175256.0, "indx": 26}, {"lat": 41.48911, "lon": -90.64542, "id": 175257.0, "indx": 27}, {"lat": 41.4865, "lon": -90.64202, "id": 175258.0, "indx": 28}, {"lat": 41.47763, "lon": -90.63052, "id": 175259.0, "indx": 29}, {"lat": 41.46899, "lon": -90.6193, "id": 175260.0, "indx": 30}, {"lat": 41.46716, "lon": -90.61755, "id": 175261.0, "indx": 31}, {"lat": 41.46165, "lon": -90.61246, "id": 175262.0, "indx": 32}, {"lat": 41.45994, "lon": -90.6103, "id": 175263.0, "indx": 33}, {"lat": 41.45831, "lon": -90.60783, "id": 175264.0, "indx": 34}, {"lat": 41.45714, "lon": -90.60542, "id": 175265.0, "indx": 35}, {"lat": 41.45484, "lon": -90.60007, "id": 175266.0, "indx": 36}, {"lat": 41.44802, "lon": -90.5837, "id": 175267.0, "indx": 37}, {"lat": 41.44709, "lon": -90.58089, "id": 175268.0, "indx": 38}, {"lat": 41.44659, "lon": -90.57826, "id": 175269.0, "indx": 39}, {"lat": 41.44638, "lon": -90.57621, "id": 175270.0, "indx": 40}, {"lat": 41.44623, "lon": -90.57349, "id": 175271.0, "indx": 41}, {"lat": 41.44627, "lon": -90.56319, "id": 175272.0, "indx": 42}, {"lat": 41.44632, "lon": -90.56132, "id": 175273.0, "indx": 43}, {"lat": 41.44673, "lon": -90.55873, "id": 175274.0, "indx": 44}, {"lat": 41.4475, "lon": -90.55627, "id": 175275.0, "indx": 45}, {"lat": 41.44855, "lon": -90.55426, "id": 175276.0, "indx": 46}, {"lat": 41.45227, "lon": -90.54919, "id": 175277.0, "indx": 47}, {"lat": 41.45369, "lon": -90.54731, "id": 175278.0, "indx": 48}, {"lat": 41.45472, "lon": -90.54549, "id": 175279.0, "indx": 49}, {"lat": 41.45545, "lon": -90.5436, "id": 175280.0, "indx": 50}, {"lat": 41.45595, "lon": -90.54179, "id": 175281.0, "indx": 51}, {"lat": 41.45623, "lon": -90.5399, "id": 175282.0, "indx": 52}, {"lat": 41.45629, "lon": -90.53793, "id": 175283.0, "indx": 53}, {"lat": 41.45635, "lon": -90.52966, "id": 175284.0, "indx": 54}, {"lat": 41.4564, "lon": -90.52348, "id": 175285.0, "indx": 55}, {"lat": 41.45652, "lon": -90.52162, "id": 175286.0, "indx": 56}, {"lat": 41.45692, "lon": -90.51941, "id": 175287.0, "indx": 57}, {"lat": 41.45763, "lon": -90.51532, "id": 175288.0, "indx": 58}, {"lat": 41.45787, "lon": -90.51321, "id": 175289.0, "indx": 59}, {"lat": 41.45796, "lon": -90.51108, "id": 175290.0, "indx": 60}, {"lat": 41.45803, "lon": -90.49818, "id": 175291.0, "indx": 61}, {"lat": 41.458, "lon": -90.4941, "id": 175292.0, "indx": 62}, {"lat": 41.4577, "lon": -90.49165, "id": 175293.0, "indx": 63}, {"lat": 41.45717, "lon": -90.48907, "id": 175294.0, "indx": 64}, {"lat": 41.4564, "lon": -90.48657, "id": 175295.0, "indx": 65}, {"lat": 41.45491, "lon": -90.48225, "id": 175296.0, "indx": 66}, {"lat": 41.45448, "lon": -90.48032, "id": 175297.0, "indx": 67}, {"lat": 41.45415, "lon": -90.47801, "id": 175298.0, "indx": 68}, {"lat": 41.45409, "lon": -90.47398, "id": 175299.0, "indx": 69}, {"lat": 41.45421, "lon": -90.46708, "id": 175300.0, "indx": 70}, {"lat": 41.45411, "lon": -90.46461, "id": 175301.0, "indx": 71}, {"lat": 41.45388, "lon": -90.46157, "id": 175302.0, "indx": 72}, {"lat": 41.4531, "lon": -90.45635, "id": 175303.0, "indx": 73}, {"lat": 41.45285, "lon": -90.45403, "id": 175304.0, "indx": 74}, {"lat": 41.45277, "lon": -90.45242, "id": 175305.0, "indx": 75}, {"lat": 41.45286, "lon": -90.44971, "id": 175306.0, "indx": 76}, {"lat": 41.45325, "lon": -90.44383, "id": 175307.0, "indx": 77}, {"lat": 41.45421, "lon": -90.42907, "id": 175308.0, "indx": 78}, {"lat": 41.4546, "lon": -90.42256, "id": 175309.0, "indx": 79}, {"lat": 41.45527, "lon": -90.41743, "id": 175310.0, "indx": 80}, {"lat": 41.45589, "lon": -90.4141, "id": 175311.0, "indx": 81}, {"lat": 41.45695, "lon": -90.4098, "id": 175312.0, "indx": 82}, {"lat": 41.45857, "lon": -90.40498, "id": 175313.0, "indx": 83}, {"lat": 41.46152, "lon": -90.39798, "id": 175314.0, "indx": 84}, {"lat": 41.46229, "lon": -90.39602, "id": 175315.0, "indx": 85}, {"lat": 41.46281, "lon": -90.39371, "id": 175316.0, "indx": 86}, {"lat": 41.46304, "lon": -90.39162, "id": 175317.0, "indx": 87}, {"lat": 41.46305, "lon": -90.38976, "id": 175318.0, "indx": 88}, {"lat": 41.46284, "lon": -90.38771, "id": 175319.0, "indx": 89}, {"lat": 41.4624, "lon": -90.3857, "id": 175320.0, "indx": 90}, {"lat": 41.46161, "lon": -90.38349, "id": 175321.0, "indx": 91}, {"lat": 41.46059, "lon": -90.38168, "id": 175322.0, "indx": 92}, {"lat": 41.45952, "lon": -90.38022, "id": 175323.0, "indx": 93}, {"lat": 41.45752, "lon": -90.37819, "id": 175324.0, "indx": 94}, {"lat": 41.44924, "lon": -90.36996, "id": 175325.0, "indx": 95}, {"lat": 41.44589, "lon": -90.36656, "id": 175326.0, "indx": 96}, {"lat": 41.44465, "lon": -90.36488, "id": 175327.0, "indx": 97}, {"lat": 41.44355, "lon": -90.363, "id": 175328.0, "indx": 98}, {"lat": 41.4426, "lon": -90.36092, "id": 175329.0, "indx": 99}, {"lat": 41.4417, "lon": -90.35823, "id": 175330.0, "indx": 100}, {"lat": 41.44105, "lon": -90.35545, "id": 175331.0, "indx": 101}, {"lat": 41.4408, "lon": -90.35281, "id": 175332.0, "indx": 102}, {"lat": 41.44069, "lon": -90.34779, "id": 175333.0, "indx": 103}, {"lat": 41.44035, "lon": -90.32984, "id": 175334.0, "indx": 104}], "ShortName": "I-280", "Cities": {"With": [{"layer": 1, "StopIndex": 103, "cityName": "Chicago", "StartIndex": 30, "cityID": 1840000494, "length": 25.265}, {"layer": 1, "StopIndex": 29, "cityName": "Rock Island", "StartIndex": 0, "cityID": 1840009233, "length": 15.648}], "Against": [{"layer": 1, "StopIndex": 38, "cityName": "Des Moines", "StartIndex": 103, "cityID": 1840007069, "length": 21.16}, {"layer": 1, "StopIndex": 0, "cityName": "Des Moines", "StartIndex": 31, "cityID": 1840007069, "length": 17.241}]}, "id": 306}